ciphercore_internal.cpython-312-x86_64-linux-gnu.so
ciphercore/__init__.py
ciphercore/internal/__init__.py
ciphercore-0.3.3.dist-info/LICENSE
ciphercore-0.3.3.dist-info/WHEEL
ciphercore-0.3.3.dist-info/top_level.txt
ciphercore-0.3.3.dist-info/RECORD
ciphercore-0.3.3.dist-info/METADATA
