Metadata-Version: 2.1
Name: ciphercore
Version: 0.3.3
Summary: Python wrapper for CipherCore base library (graph building part)
Home-page: https://github.com/ciphermodelabs/ciphercore/
Author: CipherMode
Author-email: info@ciphermode.com
License: Apache 2.0
Requires-Python: >=3.7
License-File: LICENSE
Provides-Extra: dev
Requires-Dist: numpy ; extra == 'dev'
Provides-Extra: test
Requires-Dist: pytest ; extra == 'test'
Requires-Dist: numpy ; extra == 'test'
